.class public args_many
.super java/lang/Object

.method public <init>()V
  .limit locals 1

  aload_0
  invokespecial java/lang/Object/<init>()V
  return

.end method

.method public static main([Ljava/lang/String;)V
  .limit locals 1
  .limit stack  1

  invokestatic args_many/main()I
  pop
  return

.end method


.method public static foo(IIIIIIIIIIIIIIIIIIIIIIIIIIIIIIIIIIIIIIIIIIIIIIIIIIIIIIIIIIIIIIIIIIIIIIIIIIIIIIIIIIIIIIIIIIIIIIIIIIII)I
  .limit locals 100
  .limit stack 2

	
        ;; return int (int (int (int (int (int (int (int (int (int (int (int (int (int (int (int (int (int (int (int (int (int (int (int (int (int (int (int (int (int (int (int (int (int (int (int (int (int (int (int (int (int (int (int (int (int (int (int (int (int (int (int (int (int (int (int (int (int (int (int (int (int (int (int (int (int (int (int (int (int (int (int (int (int (int (int (int (int (int (int (int (int (int (int (int (int (int (int (int (int (int (int (int (int (int (int (int (int (int (int x1) + (int x2)) + (int x3)) + (int x4)) + (int x5)) + (int x6)) + (int x7)) + (int x8)) + (int x9)) + (int x10)) + (int x11)) + (int x12)) + (int x13)) + (int x14)) + (int x15)) + (int x16)) + (int x17)) + (int x18)) + (int x19)) + (int x20)) + (int x21)) + (int x22)) + (int x23)) + (int x24)) + (int x25)) + (int x26)) + (int x27)) + (int x28)) + (int x29)) + (int x30)) + (int x31)) + (int x32)) + (int x33)) + (int x34)) + (int x35)) + (int x36)) + (int x37)) + (int x38)) + (int x39)) + (int x40)) + (int x41)) + (int x42)) + (int x43)) + (int x44)) + (int x45)) + (int x46)) + (int x47)) + (int x48)) + (int x49)) + (int x50)) + (int x51)) + (int x52)) + (int x53)) + (int x54)) + (int x55)) + (int x56)) + (int x57)) + (int x58)) + (int x59)) + (int x60)) + (int x61)) + (int x62)) + (int x63)) + (int x64)) + (int x65)) + (int x66)) + (int x67)) + (int x68)) + (int x69)) + (int x70)) + (int x71)) + (int x72)) + (int x73)) + (int x74)) + (int x75)) + (int x76)) + (int x77)) + (int x78)) + (int x79)) + (int x80)) + (int x81)) + (int x82)) + (int x83)) + (int x84)) + (int x85)) + (int x86)) + (int x87)) + (int x88)) + (int x89)) + (int x90)) + (int x91)) + (int x92)) + (int x93)) + (int x94)) + (int x95)) + (int x96)) + (int x97)) + (int x98)) + (int x99)) + (int x100);
	iload_0
	iload_1
	iadd
	iload_2
	iadd
	iload_3
	iadd
	iload 4
	iadd
	iload 5
	iadd
	iload 6
	iadd
	iload 7
	iadd
	iload 8
	iadd
	iload 9
	iadd
	iload 10
	iadd
	iload 11
	iadd
	iload 12
	iadd
	iload 13
	iadd
	iload 14
	iadd
	iload 15
	iadd
	iload 16
	iadd
	iload 17
	iadd
	iload 18
	iadd
	iload 19
	iadd
	iload 20
	iadd
	iload 21
	iadd
	iload 22
	iadd
	iload 23
	iadd
	iload 24
	iadd
	iload 25
	iadd
	iload 26
	iadd
	iload 27
	iadd
	iload 28
	iadd
	iload 29
	iadd
	iload 30
	iadd
	iload 31
	iadd
	iload 32
	iadd
	iload 33
	iadd
	iload 34
	iadd
	iload 35
	iadd
	iload 36
	iadd
	iload 37
	iadd
	iload 38
	iadd
	iload 39
	iadd
	iload 40
	iadd
	iload 41
	iadd
	iload 42
	iadd
	iload 43
	iadd
	iload 44
	iadd
	iload 45
	iadd
	iload 46
	iadd
	iload 47
	iadd
	iload 48
	iadd
	iload 49
	iadd
	iload 50
	iadd
	iload 51
	iadd
	iload 52
	iadd
	iload 53
	iadd
	iload 54
	iadd
	iload 55
	iadd
	iload 56
	iadd
	iload 57
	iadd
	iload 58
	iadd
	iload 59
	iadd
	iload 60
	iadd
	iload 61
	iadd
	iload 62
	iadd
	iload 63
	iadd
	iload 64
	iadd
	iload 65
	iadd
	iload 66
	iadd
	iload 67
	iadd
	iload 68
	iadd
	iload 69
	iadd
	iload 70
	iadd
	iload 71
	iadd
	iload 72
	iadd
	iload 73
	iadd
	iload 74
	iadd
	iload 75
	iadd
	iload 76
	iadd
	iload 77
	iadd
	iload 78
	iadd
	iload 79
	iadd
	iload 80
	iadd
	iload 81
	iadd
	iload 82
	iadd
	iload 83
	iadd
	iload 84
	iadd
	iload 85
	iadd
	iload 86
	iadd
	iload 87
	iadd
	iload 88
	iadd
	iload 89
	iadd
	iload 90
	iadd
	iload 91
	iadd
	iload 92
	iadd
	iload 93
	iadd
	iload 94
	iadd
	iload 95
	iadd
	iload 96
	iadd
	iload 97
	iadd
	iload 98
	iadd
	iload 99
	iadd
	ireturn

.end method

.method public static main()I
  .limit locals 1
  .limit stack 100

	
        ;; int x = int foo (int 1, int 2, int 3, int 4, int 5, int 6, int 7, int 8, int 9, int 10, int 11, int 12, int 13, int 14, int 15, int 16, int 17, int 18, int 19, int 20, int 21, int 22, int 23, int 24, int 25, int 26, int 27, int 28, int 29, int 30, int 31, int 32, int 33, int 34, int 35, int 36, int 37, int 38, int 39, int 40, int 41, int 42, int 43, int 44, int 45, int 46, int 47, int 48, int 49, int 50, int 51, int 52, int 53, int 54, int 55, int 56, int 57, int 58, int 59, int 60, int 61, int 62, int 63, int 64, int 65, int 66, int 67, int 68, int 69, int 70, int 71, int 72, int 73, int 74, int 75, int 76, int 77, int 78, int 79, int 80, int 81, int 82, int 83, int 84, int 85, int 86, int 87, int 88, int 89, int 90, int 91, int 92, int 93, int 94, int 95, int 96, int 97, int 98, int 99, int 100);
	iconst_1
	iconst_2
	iconst_3
	iconst_4
	iconst_5
	bipush 6
	bipush 7
	bipush 8
	bipush 9
	bipush 10
	bipush 11
	bipush 12
	bipush 13
	bipush 14
	bipush 15
	bipush 16
	bipush 17
	bipush 18
	bipush 19
	bipush 20
	bipush 21
	bipush 22
	bipush 23
	bipush 24
	bipush 25
	bipush 26
	bipush 27
	bipush 28
	bipush 29
	bipush 30
	bipush 31
	bipush 32
	bipush 33
	bipush 34
	bipush 35
	bipush 36
	bipush 37
	bipush 38
	bipush 39
	bipush 40
	bipush 41
	bipush 42
	bipush 43
	bipush 44
	bipush 45
	bipush 46
	bipush 47
	bipush 48
	bipush 49
	bipush 50
	bipush 51
	bipush 52
	bipush 53
	bipush 54
	bipush 55
	bipush 56
	bipush 57
	bipush 58
	bipush 59
	bipush 60
	bipush 61
	bipush 62
	bipush 63
	bipush 64
	bipush 65
	bipush 66
	bipush 67
	bipush 68
	bipush 69
	bipush 70
	bipush 71
	bipush 72
	bipush 73
	bipush 74
	bipush 75
	bipush 76
	bipush 77
	bipush 78
	bipush 79
	bipush 80
	bipush 81
	bipush 82
	bipush 83
	bipush 84
	bipush 85
	bipush 86
	bipush 87
	bipush 88
	bipush 89
	bipush 90
	bipush 91
	bipush 92
	bipush 93
	bipush 94
	bipush 95
	bipush 96
	bipush 97
	bipush 98
	bipush 99
	bipush 100
	invokestatic args_many/foo(IIIIIIIIIIIIIIIIIIIIIIIIIIIIIIIIIIIIIIIIIIIIIIIIIIIIIIIIIIIIIIIIIIIIIIIIIIIIIIIIIIIIIIIIIIIIIIIIIIII)I
	istore_0
	iload_0
	pop
	
        ;; void printInt (int x);
	iload_0
	invokestatic Runtime/printInt(I)V
	nop
	
        ;; return int x;
	iload_0
	ireturn

.end method
